char/__init__.py
char/main.py
char-0.1.2.dist-info/AUTHORS.rst
char-0.1.2.dist-info/LICENSE.txt
char-0.1.2.dist-info/METADATA
char-0.1.2.dist-info/WHEEL
char-0.1.2.dist-info/top_level.txt
char-0.1.2.dist-info/RECORD
